code_recorder_processor/__init__.py
code_recorder_processor/api/build.py
code_recorder_processor/api/document.py
code_recorder_processor/api/load.py
code_recorder_processor/api/output.py
code_recorder_processor/api/verify.py
code_recorder_processor/cli.py
code_recorder_processor/display.py
code_recorder_processor/playback.py
cr_proc-0.1.12.dist-info/METADATA
cr_proc-0.1.12.dist-info/WHEEL
cr_proc-0.1.12.dist-info/entry_points.txt
cr_proc-0.1.12.dist-info/RECORD
