Metadata-Version: 2.4
Name: cr_proc
Version: 0.1.12
Summary: A tool for processing BYU CS code recording files.
Author: Ethan Dye
Author-email: mrtops03@gmail.com
Requires-Python: >=3.14
Classifier: Programming Language :: Python :: 3
Classifier: Programming Language :: Python :: 3.14
Requires-Dist: py-jsonl (>=1.3.22,<2.0.0)
